moatless/__init__.py
moatless/actions/__init__.py
moatless/actions/action.py
moatless/actions/append_string.py
moatless/actions/claude_text_editor.py
moatless/actions/code_action_value_mixin.py
moatless/actions/code_modification_mixin.py
moatless/actions/create_file.py
moatless/actions/find_class.py
moatless/actions/find_code_snippet.py
moatless/actions/find_function.py
moatless/actions/finish.py
moatless/actions/identify_mixin.py
moatless/actions/insert_line.py
moatless/actions/list_files.py
moatless/actions/reject.py
moatless/actions/respond.py
moatless/actions/run_tests.py
moatless/actions/schema.py
moatless/actions/search_base.py
moatless/actions/semantic_search.py
moatless/actions/string_replace.py
moatless/actions/verified_finish.py
moatless/actions/view_code.py
moatless/actions/view_diff.py
moatless/agent/__init__.py
moatless/agent/agent.py
moatless/agent/code_agent.py
moatless/agent/code_prompts.py
moatless/agent/settings.py
moatless/api/__init__.py
moatless/api/api.py
moatless/api/schema.py
moatless/api/trajectory_utils.py
moatless/artifacts/__init__.py
moatless/artifacts/artifact.py
moatless/artifacts/file.py
moatless/benchmark/__init__.py
moatless/benchmark/create_dataset.py
moatless/benchmark/evaluation_factory.py
moatless/benchmark/evaluation_runner.py
moatless/benchmark/report.py
moatless/benchmark/repository.py
moatless/benchmark/run_evaluation.py
moatless/benchmark/schema.py
moatless/benchmark/swebench/__init__.py
moatless/benchmark/swebench/utils.py
moatless/benchmark/swebench_lite_all_evaluations.json
moatless/benchmark/swebench_verified_all_evaluations.json
moatless/benchmark/utils.py
moatless/build.py
moatless/chat.py
moatless/codeblocks/__init__.py
moatless/codeblocks/codeblocks.py
moatless/codeblocks/module.py
moatless/codeblocks/parser/__init__.py
moatless/codeblocks/parser/comment.py
moatless/codeblocks/parser/create.py
moatless/codeblocks/parser/java.py
moatless/codeblocks/parser/parser.py
moatless/codeblocks/parser/python.py
moatless-0.0.12.dist-info/LICENSE
moatless-0.0.12.dist-info/METADATA
moatless-0.0.12.dist-info/WHEEL
moatless-0.0.12.dist-info/entry_points.txt
moatless-0.0.12.dist-info/RECORD
