Metadata-Version: 2.3
Name: moatless
Version: 0.0.12
Summary: 
Author: Albert Örwall
Author-email: albert@moatless.ai
Requires-Python: >=3.11,<3.13
Classifier: Programming Language :: Python :: 3
Classifier: Programming Language :: Python :: 3.11
Classifier: Programming Language :: Python :: 3.12
Provides-Extra: all
Provides-Extra: api
Provides-Extra: streamlit
Requires-Dist: anthropic (>=0.38.0,<0.39.0)
Requires-Dist: boto3 (>=1.35.54,<2.0.0)
Requires-Dist: botocore (>=1.35.54,<2.0.0)
Requires-Dist: click (>=8.1.7,<9.0.0) ; extra == "api" or extra == "all"
Requires-Dist: docstring-parser (>=0.16,<0.17)
Requires-Dist: faiss-cpu (>=1.8.0.post1,<2.0.0)
Requires-Dist: fastapi (>=0.115.7,<0.116.0) ; extra == "api" or extra == "all"
Requires-Dist: filelock (>=3.16.1,<4.0.0)
Requires-Dist: gitpython (>=3.1.43,<4.0.0)
Requires-Dist: instructor (<=1.6.3)
Requires-Dist: litellm (>=1.59.3,<2.0.0)
Requires-Dist: llama-index (>=0.12.11,<0.13.0)
Requires-Dist: llama-index-embeddings-openai (>=0.3.1,<0.4.0)
Requires-Dist: llama-index-embeddings-voyageai (>=0.3.4,<0.4.0)
Requires-Dist: llama-index-readers-file (>=0.4.3,<0.5.0)
Requires-Dist: moatless-testbeds (>=0.0.12,<0.0.13)
Requires-Dist: networkx (>=3.3,<4.0)
Requires-Dist: numpy (>=1.0,<2.0)
Requires-Dist: openai (>=1.41.0,<2.0.0)
Requires-Dist: plotly (>=5.24.1,<6.0.0) ; extra == "streamlit" or extra == "all"
Requires-Dist: pydantic (>=2.8.2,<3.0.0)
Requires-Dist: pygraphviz (>=1.14,<2.0) ; extra == "streamlit" or extra == "all"
Requires-Dist: pylint (>=3.2.6,<4.0.0)
Requires-Dist: python-dotenv (==1.0.1)
Requires-Dist: python-multipart (>=0.0.20,<0.0.21) ; extra == "api" or extra == "all"
Requires-Dist: rapidfuzz (>=3.9.5,<4.0.0)
Requires-Dist: scikit-learn (>=1.6.1,<2.0.0) ; extra == "streamlit" or extra == "all"
Requires-Dist: streamlit (>=1.41.1,<2.0.0) ; extra == "streamlit" or extra == "all"
Requires-Dist: tiktoken (>=0.8.0,<0.9.0)
Requires-Dist: tree-sitter (==0.24.0)
Requires-Dist: tree-sitter-java (==0.23.5)
Requires-Dist: tree-sitter-python (==0.23.6)
Requires-Dist: unidiff (>=0.7.5,<0.8.0)
Requires-Dist: uvicorn (>=0.34.0,<0.35.0) ; extra == "api" or extra == "all"
Requires-Dist: voyageai (>=0.3.2,<0.4.0)
